{
    "county":{
        "England":{
            "GB-BKM":"Buckinghamshire",
            "GB-CAM":"Cambridgeshire",
            "GB-CMA":"Cumbria",
            "GB-DBY":"Derbyshire",
            "GB-DEV":"Devon",
            "GB-DOR":"Dorset",
            "GB-ESX":"East Sussex",
            "GB-ESS":"Essex",
            "GB-GLS":"Gloucestershire",
            "GB-HAM":"Hampshire",
            "GB-HRT":"Hertfordshire",
            "GB-KEN":"Kent",
            "GB-LAN":"Lancashire",
            "GB-LEC":"Leicestershire",
            "GB-LIN":"Lincolnshire",
            "GB-NFK":"Norfolk",
            "GB-NYK":"North Yorkshire",
            "GB-NTH":"Northamptonshire",
            "GB-NTT":"Nottinghamshire",
            "GB-OXF":"Oxfordshire",
            "GB-SOM":"Somerset",
            "GB-STS":"Staffordshire",
            "GB-SFK":"Suffolk",
            "GB-SRY":"Surrey",
            "GB-WAR":"Warwickshire",
            "GB-WSX":"West Sussex",
            "GB-WOR":"Worcestershire",
            "GB-BAS":"Bath and North East Somerset",
            "GB-BBD":"Blackburn with Darwen",
            "GB-BDF":"Bedford",
            "GB-BPL":"Blackpool",
            "GB-BMH":"Bournemouth",
            "GB-BRC":"Bracknell Forest",
            "GB-BNH":"Brighton and Hove",
            "GB-BST":"Bristol",
            "GB-CBF":"Central Bedfordshire",
            "GB-CHE":"Cheshire East",
            "GB-CHW":"Cheshire West and Chester",
            "GB-CON":"Cornwall",
            "GB-DAL":"Darlington",
            "GB-DER":"Derby",
            "GB-DUR":"Durham",
            "GB-ERY":"East Riding of Yorkshire",
            "GB-HAL":"Halton",
            "GB-HPL":"Hartlepool",
            "GB-HEF":"Herefordshire",
            "GB-IOW":"Isle of Wight",
            "GB-KHL":"Kingston upon Hull",
            "GB-LCE":"Leicester",
            "GB-LUT":"Luton",
            "GB-MDW":"Medway",
            "GB-MDB":"Middlesbrough",
            "GB-MIK":"Milton Keynes",
            "GB-NEL":"North East Lincolnshire",
            "GB-NLN":"North Lincolnshire",
            "GB-NSM":"North Somerset",
            "GB-NBL":"Northumberland",
            "GB-NGM":"Nottingham",
            "GB-PTE":"Peterborough",
            "GB-PLY":"Plymouth",
            "GB-POL":"Poole",
            "GB-POR":"Portsmouth",
            "GB-RDG":"Reading",
            "GB-RCC":"Redcar and Cleveland",
            "GB-RUT":"Rutland",
            "GB-SHR":"Shropshire",
            "GB-SLG":"Slough",
            "GB-SGC":"South Gloucestershire",
            "GB-STH":"Southampton",
            "GB-SOS":"Southend-on-Sea",
            "GB-STT":"Stockton-on-Tees",
            "GB-STE":"Stoke-on-Trent",
            "GB-SWD":"Swindon",
            "GB-TFW":"Telford and Wrekin",
            "GB-THR":"Thurrock",
            "GB-TOB":"Torbay",
            "GB-WRT":"Warrington",
            "GB-WBK":"West Berkshire",
            "GB-WIL":"Wiltshire",
            "GB-WNM":"Windsor and Maidenhead",
            "GB-WOK":"Wokingham",
            "GB-YOR":"York"
        },
        "Northern Ireland":{
            "GB-ANT":"Antrim",
            "GB-ARD":"Ards",
            "GB-ARM":"Armagh",
            "GB-BLA":"Ballymena",
            "GB-BLY":"Ballymoney",
            "GB-BNB":"Banbridge",
            "GB-BFS":"Belfast",
            "GB-CKF":"Carrickfergus",
            "GB-CSR":"Castlereagh",
            "GB-CLR":"Coleraine",
            "GB-CKT":"Cookstown",
            "GB-CGV":"Craigavon",
            "GB-DRY":"Derry",
            "GB-DOW":"Down",
            "GB-DGN":"Dungannon and South Tyrone",
            "GB-FER":"Fermanagh",
            "GB-LRN":"Larne",
            "GB-LMV":"Limavady",
            "GB-LSB":"Lisburn",
            "GB-MFT":"Magherafelt",
            "GB-MYL":"Moyle",
            "GB-NYM":"Newry and Mourne District",
            "GB-NTA":"Newtownabbey",
            "GB-NDN":"North Down",
            "GB-OMH":"Omagh",
            "GB-STB":"Strabane"
        },
        "Scotland":{
            "GB-ABE":"Aberdeen City",
            "GB-ABD":"Aberdeenshire",
            "GB-ANS":"Angus",
            "GB-AGB":"Argyll and Bute",
            "GB-CLK":"Clackmannanshire",
            "GB-DGY":"Dumfries and Galloway",
            "GB-DND":"Dundee City",
            "GB-EAY":"East Ayrshire",
            "GB-EDU":"East Dunbartonshire",
            "GB-ELN":"East Lothian",
            "GB-ERW":"East Renfrewshire",
            "GB-EDH":"Edinburgh",
            "GB-ELS":"Eilean Siar",
            "GB-FAL":"Falkirk",
            "GB-FIF":"Fife",
            "GB-GLG":"Glasgow City",
            "GB-HLD":"Highland",
            "GB-IVC":"Inverclyde",
            "GB-MLN":"Midlothian",
            "GB-MRY":"Moray",
            "GB-NAY":"North Ayrshire",
            "GB-NLK":"North Lanarkshire",
            "GB-ORK":"Orkney Islands",
            "GB-PKN":"Perth and Kinross",
            "GB-RFW":"Renfrewshire",
            "GB-SCB":"Scottish Borders",
            "GB-ZET":"Shetland Islands",
            "GB-SAY":"South Ayrshire",
            "GB-SLK":"South Lanarkshire",
            "GB-STG":"Stirling",
            "GB-WDU":"West Dunbartonshire",
            "GB-WLN":"West Lothian"
        },
        "Wales":{
            "GB-BGW":"Blaenau Gwent",
            "GB-BGE":"Bridgend (Pen-y-bont ar Ogwr)",
            "GB-CAY":"Caerphilly (Caerffili)",
            "GB-CRF":"Cardiff (Caerdydd)",
            "GB-CMN":"Carmarthenshire (Sir Gaerfyrddin)",
            "GB-CGN":"Ceredigion (Sir Ceredigion)",
            "GB-CWY":"Conwy",
            "GB-DEN":"Denbighshire (Sir Ddinbych)",
            "GB-FLN":"Flintshire (Sir y Fflint)",
            "GB-GWN":"Gwynedd",
            "GB-AGY":"Isle of Anglesey (Sir Ynys M\u00f4n)",
            "GB-MTY":"Merthyr Tydfil (Merthyr Tudful)",
            "GB-MON":"Monmouthshire (Sir Fynwy)",
            "GB-NTL":"Neath Port Talbot (Castell-nedd Port Talbot)",
            "GB-NWP":"Newport (Casnewydd)",
            "GB-PEM":"Pembrokeshire (Sir Benfro)",
            "GB-POW":"Powys",
            "GB-RCT":"Rhondda, Cynon, Taff",
            "GB-SWA":"Swansea (Abertawe)",
            "GB-TOF":"Torfaen (Tor-faen)",
            "GB-VGL":"Vale of Glamorgan (Bro Morgannwg)",
            "GB-WRX":"Wrexham (Wrecsam)"
        }
    }
}
